LbSoftConfDB/AppImporter.py
LbSoftConfDB/LbSdbAddPlatform.py
LbSoftConfDB/LbSdbBuildTool.py
LbSoftConfDB/LbSdbDeleteVersion.py
LbSoftConfDB/LbSdbDumpProjects.py
LbSoftConfDB/LbSdbGenerateVersionJSON.py
LbSoftConfDB/LbSdbImport.py
LbSoftConfDB/LbSdbQuery.py
LbSoftConfDB/LbSdbRelease.py
LbSoftConfDB/LbSdbSetPVProperties.py
LbSoftConfDB/LbSdbSetProjectProperties.py
LbSoftConfDB/SoftConfDB.py
LbSoftConfDB/SoftConfDBRO.py
LbSoftConfDB/__init__.py
LbSoftConfDB-0.0.4.dist-info/DESCRIPTION.rst
LbSoftConfDB-0.0.4.dist-info/METADATA
LbSoftConfDB-0.0.4.dist-info/RECORD
LbSoftConfDB-0.0.4.dist-info/WHEEL
LbSoftConfDB-0.0.4.dist-info/entry_points.txt
LbSoftConfDB-0.0.4.dist-info/metadata.json
LbSoftConfDB-0.0.4.dist-info/top_level.txt
LbSoftConfDB-0.0.4.dist-info/zip-safe
