Metadata-Version: 2.0
Name: LbSoftConfDB
Version: 0.0.4
Summary: LHCb Software configuration database
Home-page: https://gitlab.cern.ch/lhcb-core/LbSoftConfDB
Author: CERN - LHCb Core Software
Author-email: lhcb-core-soft@cern.ch
License: GPLv3+
Platform: UNKNOWN
Classifier: Development Status :: 4 - Beta
Classifier: Intended Audience :: Developers
Classifier: Topic :: Software Development :: Build Tools
Classifier: License :: OSI Approved :: GNU General Public License v3 or later (GPLv3+)
Classifier: Programming Language :: Python :: 2
Classifier: Programming Language :: Python :: 2.7
Classifier: Programming Language :: Python :: 3
Classifier: Programming Language :: Python :: 3.5
Classifier: Programming Language :: Python :: 3.6
Requires-Python: >=2.7, !=3.0.*, !=3.1.*, !=3.2.*, !=3.3.*, !=3.4.*, <4
Requires-Dist: py2neo (==1.4.6)
Requires-Dist: LbCommon
Requires-Dist: LbEnv
